CHANGES.txt
README.txt
__init__.py
setup.py
version.txt
zopyx/__init__.py
zopyx.textindexng3.egg-info/PKG-INFO
zopyx.textindexng3.egg-info/SOURCES.txt
zopyx.textindexng3.egg-info/dependency_links.txt
zopyx.textindexng3.egg-info/namespace_packages.txt
zopyx.textindexng3.egg-info/requires.txt
zopyx.textindexng3.egg-info/top_level.txt
zopyx/txng3/__init__.py
zopyx/txng3/support.c
zopyx/txng3/normalizer/__init__.py
zopyx/txng3/normalizer/normalizer.c
zopyx/txng3/normalizer/tests/__init__.py
zopyx/txng3/normalizer/tests/testNormalizer.py
zopyx/txng3/python-Levenshtein-0.10/COPYING
zopyx/txng3/python-Levenshtein-0.10/Levenshtein.c
zopyx/txng3/python-Levenshtein-0.10/Levenshtein.h
zopyx/txng3/python-Levenshtein-0.10/MANIFEST
zopyx/txng3/python-Levenshtein-0.10/NEWS
zopyx/txng3/python-Levenshtein-0.10/PKG-INFO
zopyx/txng3/python-Levenshtein-0.10/README
zopyx/txng3/python-Levenshtein-0.10/StringMatcher.py
zopyx/txng3/python-Levenshtein-0.10/gendoc.sh
zopyx/txng3/python-Levenshtein-0.10/setup.cfg
zopyx/txng3/python-Levenshtein-0.10/setup.py
zopyx/txng3/splitter/LICENSE
zopyx/txng3/splitter/__init__.py
zopyx/txng3/splitter/dict.c
zopyx/txng3/splitter/dict.h
zopyx/txng3/splitter/dict_private.h
zopyx/txng3/splitter/hashtable.c
zopyx/txng3/splitter/hashtable.h
zopyx/txng3/splitter/splitter.c
zopyx/txng3/splitter/tests/__init__.py
zopyx/txng3/splitter/tests/testTXNGSplitter.py
zopyx/txng3/stemmer/__init__.py
zopyx/txng3/stemmer/stemmer.c
zopyx/txng3/stemmer/libstemmer_c/MANIFEST
zopyx/txng3/stemmer/libstemmer_c/Makefile
zopyx/txng3/stemmer/libstemmer_c/README
zopyx/txng3/stemmer/libstemmer_c/mkinc.mak
zopyx/txng3/stemmer/libstemmer_c/modules.h
zopyx/txng3/stemmer/libstemmer_c/examples/stemwords.c
zopyx/txng3/stemmer/libstemmer_c/include/libstemmer.h
zopyx/txng3/stemmer/libstemmer_c/libstemmer/libstemmer.c
zopyx/txng3/stemmer/libstemmer_c/libstemmer/modules.h
zopyx/txng3/stemmer/libstemmer_c/runtime/api.c
zopyx/txng3/stemmer/libstemmer_c/runtime/api.h
zopyx/txng3/stemmer/libstemmer_c/runtime/header.h
zopyx/txng3/stemmer/libstemmer_c/runtime/utilities.c
zopyx/txng3/stemmer/libstemmer_c/src_c/stem_ISO_8859_1_danish.c
zopyx/txng3/stemmer/libstemmer_c/src_c/stem_ISO_8859_1_danish.h
