Metadata-Version: 1.0
Name: zopyx.textindexng3
Version: 4.0.1
Summary: Helper modules for TextIndexNG3 (Snowball stemmer, normalizer, splitter, etc.)
Home-page: http://sf.net/projects/textindexng/
Author: Andreas Jung, ZOPYX Ltd. & Co. KG
Author-email: info@zopyx.com
License: UNKNOWN
Platform: UNKNOWN
